{
    "base": "/sg2004/031404/",
    "title": "Mar 14, 2004 T6.7 'Be Vigilant Only for God and His Kingdom'",
    "time": [{
        "id": "p0",
        "seconds": 0
    }, {
        "id": "p1",
        "seconds": 13.777625
    }, {
        "id": "p2",
        "seconds": 85.575625
    }, {
        "id": "p3",
        "seconds": 135.258041
    }, {
        "id": "p4",
        "seconds": 187.768291
    }, {
        "id": "p5",
        "seconds": 244.267312
    }, {
        "id": "p6",
        "seconds": 293.643291
    }, {
        "id": "p7",
        "seconds": 304.156125
    }, {
        "id": "p8",
        "seconds": 340.2215
    }, {
        "id": "p9",
        "seconds": 414.039208
    }, {
        "id": "p10",
        "seconds": 510.271854
    }, {
        "id": "p11",
        "seconds": 633.73652
    }, {
        "id": "p12",
        "seconds": 709.539791
    }, {
        "id": "p13",
        "seconds": 802.610541
    }, {
        "id": "p14",
        "seconds": 901.352958
    }, {
        "id": "p15",
        "seconds": 1004.100083
    }, {
        "id": "p16",
        "seconds": 1006.938666
    }, {
        "id": "p17",
        "seconds": 1022.8405
    }, {
        "id": "p18",
        "seconds": 1064.852791
    }, {
        "id": "p19",
        "seconds": 1125.58977
    }, {
        "id": "p20",
        "seconds": 1127.008437
    }, {
        "id": "p21",
        "seconds": 1134.66975
    }, {
        "id": "p22",
        "seconds": 1138.078937
    }, {
        "id": "p23",
        "seconds": 1156.236083
    }, {
        "id": "p24",
        "seconds": 1161.625333
    }, {
        "id": "p25",
        "seconds": 1245.369395
    }, {
        "id": "p26",
        "seconds": 1274.32777
    }, {
        "id": "p27",
        "seconds": 1321.759125
    }, {
        "id": "p28",
        "seconds": 1336.810208
    }, {
        "id": "p29",
        "seconds": 1363.218062
    }, {
        "id": "p30",
        "seconds": 1400.687125
    }, {
        "id": "p31",
        "seconds": 1414.599979
    }, {
        "id": "p32",
        "seconds": 1423.119583
    }, {
        "id": "p33",
        "seconds": 1454.910125
    }, {
        "id": "p34",
        "seconds": 1456.897916
    }, {
        "id": "p35",
        "seconds": 1487.275416
    }, {
        "id": "p36",
        "seconds": 1555.394562
    }, {
        "id": "p37",
        "seconds": 1605.356729
    }, {
        "id": "p38",
        "seconds": 1658.71527
    }, {
        "id": "p39",
        "seconds": 1723.162958
    }, {
        "id": "p40",
        "seconds": 1769.423437
    }, {
        "id": "p41",
        "seconds": 1771.9765
    }, {
        "id": "p42",
        "seconds": 1786.45152
    }, {
        "id": "p43",
        "seconds": 1819.3915
    }, {
        "id": "p44",
        "seconds": 1870.481479
    }, {
        "id": "p45",
        "seconds": 1903.103187
    }, {
        "id": "p46",
        "seconds": 2024.014333
    }, {
        "id": "p47",
        "seconds": 2064.020458
    }, {
        "id": "p48",
        "seconds": 2152.313312
    }, {
        "id": "p49",
        "seconds": 2195.46825
    }, {
        "id": "p50",
        "seconds": 2197.739479
    }, {
        "id": "p51",
        "seconds": 2232.366895
    }, {
        "id": "p52",
        "seconds": 2255.347062
    }, {
        "id": "p53",
        "seconds": 2294.245291
    }, {
        "id": "p54",
        "seconds": 2323.768937
    }, {
        "id": "p55",
        "seconds": 2329.735833
    }, {
        "id": "p56",
        "seconds": 2332.00477
    }, {
        "id": "p57",
        "seconds": 2377.702083
    }, {
        "id": "p58",
        "seconds": 2382.807833
    }, {
        "id": "p59",
        "seconds": 2386.505458
    }, {
        "id": "p60",
        "seconds": 2403.817375
    }, {
        "id": "p61",
        "seconds": 2423.410708
    }, {
        "id": "p62",
        "seconds": 2441.295604
    }, {
        "id": "p63",
        "seconds": 2474.798916
    }, {
        "id": "p64",
        "seconds": 2477.353229
    }, {
        "id": "p65",
        "seconds": 2486.720916
    }, {
        "id": "p66",
        "seconds": 2490.698041
    }, {
        "id": "p67",
        "seconds": 2506.59275
    }, {
        "id": "p68",
        "seconds": 2508.582291
    }, {
        "id": "p69",
        "seconds": 2522.774895
    }, {
        "id": "p70",
        "seconds": 2535.549062
    }, {
        "id": "p71",
        "seconds": 2538.955645
    }, {
        "id": "p72",
        "seconds": 2545.486083
    }, {
        "id": "p73",
        "seconds": 2574.164145
    }, {
        "id": "p74",
        "seconds": 2649.948416
    }, {
        "id": "p75",
        "seconds": 2701.618166
    }, {
        "id": "p76",
        "seconds": 2774.560895
    }, {
        "id": "p77",
        "seconds": 2817.991395
    }, {
        "id": "p78",
        "seconds": 2871.345958
    }, {
        "id": "p79",
        "seconds": 2901.741312
    }, {
        "id": "p80",
        "seconds": 2948.580833
    }, {
        "id": "p81",
        "seconds": 2993.997208
    }, {
        "id": "p82",
        "seconds": 3061.545791
    }, {
        "id": "p83",
        "seconds": 3088.23427
    }, {
        "id": "p84",
        "seconds": 3089.371187
    }, {
        "id": "p85",
        "seconds": 3099.584666
    }, {
        "id": "p86",
        "seconds": 3119.472145
    }, {
        "id": "p87",
        "seconds": 3143.86502
    }, {
        "id": "p88",
        "seconds": 3146.701979
    }, {
        "id": "p89",
        "seconds": 3155.508583
    }, {
        "id": "p90",
        "seconds": 3209.421583
    }, {
        "id": "p91",
        "seconds": 3251.155333
    }, {
        "id": "p92",
        "seconds": 3319.287187
    }, {
        "id": "p93",
        "seconds": 3339.443666
    }, {
        "id": "p94",
        "seconds": 3341.431812
    }, {
        "id": "p95",
        "seconds": 3359.879729
    }, {
        "id": "p96",
        "seconds": 3363.565958
    }, {
        "id": "p97",
        "seconds": 3369.813
    }, {
        "id": "p98",
        "seconds": 3382.879875
    }, {
        "id": "p99",
        "seconds": 3454.0955
    }, {
        "id": "p100",
        "seconds": 3456.64902
    }, {
        "id": "p101",
        "seconds": 3488.425916
    }, {
        "id": "p102",
        "seconds": 3512.00552
    }, {
        "id": "p103",
        "seconds": 3514.276333
    }, {
        "id": "p104",
        "seconds": 3537.850416
    }, {
        "id": "p105",
        "seconds": 3600.887333
    }, {
        "id": "p106",
        "seconds": 3676.956791
    }, {
        "id": "p107",
        "seconds": 3737.394937
    }, {
        "id": "p108",
        "seconds": 3836.684354
    }, {
        "id": "p109",
        "seconds": 3860.233541
    }, {
        "id": "p110",
        "seconds": 3863.64102
    }, {
        "id": "p111",
        "seconds": 3867.623187
    }, {
        "id": "p112",
        "seconds": 3869.041583
    }, {
        "id": "p113",
        "seconds": 3883.799791
    }, {
        "id": "p114",
        "seconds": 3887.211208
    }, {
        "id": "p115",
        "seconds": 3931.203187
    }, {
        "id": "p116",
        "seconds": 3939.71977
    }, {
        "id": "p117",
        "seconds": 3954.198583
    }, {
        "id": "p118",
        "seconds": 4020.656979
    }, {
        "id": "p119",
        "seconds": 4131.35752
    }, {
        "id": "p120",
        "seconds": 4163.162229
    }]
}
