{
    "base": "/sg2009/041209/",
    "title": "Apr 12, 2009 T15.3 Littleness versus Magnitude",
    "time": [{
        "id": "p0",
        "seconds": 0
    }, {
        "id": "p1",
        "seconds": 11.724229
    }, {
        "id": "p2",
        "seconds": 67.801812
    }, {
        "id": "p3",
        "seconds": 139.799145
    }, {
        "id": "p4",
        "seconds": 201.06175
    }, {
        "id": "p5",
        "seconds": 254.360395
    }, {
        "id": "p6",
        "seconds": 280.453437
    }, {
        "id": "p7",
        "seconds": 347.078437
    }, {
        "id": "p8",
        "seconds": 374.563645
    }, {
        "id": "p9",
        "seconds": 430.691125
    }, {
        "id": "p10",
        "seconds": 516.302541
    }, {
        "id": "p11",
        "seconds": 575.529583
    }, {
        "id": "p12",
        "seconds": 659.426666
    }, {
        "id": "p13",
        "seconds": 673.048166
    }, {
        "id": "p14",
        "seconds": 753.87302
    }, {
        "id": "p15",
        "seconds": 760.963041
    }, {
        "id": "p16",
        "seconds": 777.710479
    }, {
        "id": "p17",
        "seconds": 830.427791
    }, {
        "id": "p18",
        "seconds": 904.394874
    }, {
        "id": "p19",
        "seconds": 914.544353
    }, {
        "id": "p20",
        "seconds": 985.733228
    }, {
        "id": "p21",
        "seconds": 993.67502
    }, {
        "id": "p22",
        "seconds": 995.381457
    }, {
        "id": "p23",
        "seconds": 998.787832
    }, {
        "id": "p24",
        "seconds": 1013.251978
    }, {
        "id": "p25",
        "seconds": 1022.89652
    }, {
        "id": "p26",
        "seconds": 1052.40377
    }, {
        "id": "p27",
        "seconds": 1088.114145
    }, {
        "id": "p28",
        "seconds": 1111.293436
    }, {
        "id": "p29",
        "seconds": 1124.045186
    }, {
        "id": "p30",
        "seconds": 1177.608332
    }, {
        "id": "p31",
        "seconds": 1191.504332
    }, {
        "id": "p32",
        "seconds": 1230.637436
    }, {
        "id": "p33",
        "seconds": 1268.354894
    }, {
        "id": "p34",
        "seconds": 1282.822165
    }, {
        "id": "p35",
        "seconds": 1292.465269
    }, {
        "id": "p36",
        "seconds": 1301.262728
    }, {
        "id": "p37",
        "seconds": 1365.598124
    }, {
        "id": "p38",
        "seconds": 1370.709561
    }, {
        "id": "p39",
        "seconds": 1377.514436
    }, {
        "id": "p40",
        "seconds": 1389.940999
    }, {
        "id": "p41",
        "seconds": 1415.47854
    }, {
        "id": "p42",
        "seconds": 1421.156082
    }, {
        "id": "p43",
        "seconds": 1425.979228
    }, {
        "id": "p44",
        "seconds": 1430.516394
    }, {
        "id": "p45",
        "seconds": 1434.20929
    }, {
        "id": "p46",
        "seconds": 1437.89729
    }, {
        "id": "p47",
        "seconds": 1441.022499
    }, {
        "id": "p48",
        "seconds": 1446.985249
    }, {
        "id": "p49",
        "seconds": 1468.239164
    }, {
        "id": "p50",
        "seconds": 1489.815873
    }, {
        "id": "p51",
        "seconds": 1564.983748
    }, {
        "id": "p52",
        "seconds": 1613.460227
    }, {
        "id": "p53",
        "seconds": 1661.346685
    }, {
        "id": "p54",
        "seconds": 1681.764227
    }, {
        "id": "p55",
        "seconds": 1697.077289
    }, {
        "id": "p56",
        "seconds": 1709.846185
    }, {
        "id": "p57",
        "seconds": 1794.308664
    }, {
        "id": "p58",
        "seconds": 1865.783769
    }, {
        "id": "p59",
        "seconds": 1945.754394
    }, {
        "id": "p60",
        "seconds": 1950.87306
    }, {
        "id": "p61",
        "seconds": 1955.986123
    }, {
        "id": "p62",
        "seconds": 2018.913373
    }, {
        "id": "p63",
        "seconds": 2039.601081
    }, {
        "id": "p64",
        "seconds": 2074.197748
    }, {
        "id": "p65",
        "seconds": 2075.049644
    }, {
        "id": "p66",
        "seconds": 2095.469956
    }, {
        "id": "p67",
        "seconds": 2114.756226
    }, {
        "id": "p68",
        "seconds": 2120.144143
    }, {
        "id": "p69",
        "seconds": 2225.27056
    }, {
        "id": "p70",
        "seconds": 2248.218955
    }, {
        "id": "p71",
        "seconds": 2278.289039
    }, {
        "id": "p72",
        "seconds": 2312.878726
    }, {
        "id": "p73",
        "seconds": 2385.724539
    }, {
        "id": "p74",
        "seconds": 2458.28483
    }, {
        "id": "p75",
        "seconds": 2501.962685
    }, {
        "id": "p76",
        "seconds": 2513.301685
    }, {
        "id": "p77",
        "seconds": 2539.674351
    }, {
        "id": "p78",
        "seconds": 2615.977914
    }, {
        "id": "p79",
        "seconds": 2755.438414
    }, {
        "id": "p80",
        "seconds": 2812.126518
    }, {
        "id": "p81",
        "seconds": 2879.307018
    }]
}
